AUTHORS.rst
CONTRIBUTING.rst
HISTORY.rst
LICENSE
MANIFEST.in
README.rst
setup.cfg
setup.py
Jobber/DRMAAJobExecuter.py
Jobber/Executer.py
Jobber/Executers.py
Jobber/JobClient.py
Jobber/JobController.py
Jobber/JobExecuter.py
Jobber/LocalJobExecuter.py
Jobber/Logging.py
Jobber/Native.py
Jobber/Settings.py
Jobber/TestJobExecuter.py
Jobber/__init__.py
Jobber.egg-info/PKG-INFO
Jobber.egg-info/SOURCES.txt
Jobber.egg-info/dependency_links.txt
Jobber.egg-info/not-zip-safe
Jobber.egg-info/pbr.json
Jobber.egg-info/top_level.txt
Jobber/database/.gitignore
Jobber/database/Connection.py
Jobber/database/JobAction.py
Jobber/database/JobCreator.py
Jobber/database/JobDAO.py
Jobber/database/JobDatabase.sql
Jobber/database/JobDatabaseSQLite.sql
Jobber/database/JobStatus.py
Jobber/database/Mysql.py
Jobber/database/Sqlite3.py
Jobber/database/__init__.py
Jobber/web/.bash_history
Jobber/web/draw_graph.py
Jobber/web/static/css/.bash_history
Jobber/web/static/css/bootstrap-table.css
Jobber/web/static/css/bootstrap-theme.css
Jobber/web/static/css/bootstrap-theme.css.map
Jobber/web/static/css/bootstrap-theme.min.css
Jobber/web/static/css/bootstrap.css
Jobber/web/static/css/bootstrap.css.map
Jobber/web/static/css/bootstrap.min.css
Jobber/web/static/css/styles.css
Jobber/web/static/fonts/glyphicons-halflings-regular.eot
Jobber/web/static/fonts/glyphicons-halflings-regular.svg
Jobber/web/static/fonts/glyphicons-halflings-regular.ttf
Jobber/web/static/fonts/glyphicons-halflings-regular.woff
Jobber/web/static/fonts/glyphicons-halflings-regular.woff2
Jobber/web/static/images/._SIB_logo.png
Jobber/web/static/images/._overview.png
Jobber/web/static/images/BZ_logo.png
Jobber/web/static/images/SIB_logo.png
Jobber/web/static/images/favicon.png
Jobber/web/static/images/favicon.svg
Jobber/web/static/js/.bash_history
Jobber/web/static/js/alert.js
Jobber/web/static/js/bootstrap-table.js
Jobber/web/static/js/bootstrap.js
Jobber/web/static/js/bootstrap.min.js
Jobber/web/static/js/modal.js
Jobber/web/static/js/npm.js
Jobber/web/static/js/popover.js
Jobber/web/static/js/scripts.js
Jobber/web/static/js/tooltip.js
Jobber/web/static/js/transition.js
