Metadata-Version: 1.1
Name: Jobber
Version: 0.1.1
Summary: Jobber is a program that executes pipelines. It manages job dependencies, restarts them if necessary and logs their status in a database. Jobs are persisted in a database and survive system crashes.
Home-page: https://git.scicore.unibas.ch/AnnotationPipelines/Jobber
Author: Christoph Rodak
Author-email: christoph@rodak.li
License: BSD
Keywords: Jobber
Platform: UNKNOWN
Classifier: Development Status :: 4 - Beta
Classifier: Intended Audience :: Developers
Classifier: License :: OSI Approved :: BSD License
Classifier: Natural Language :: English
Classifier: Programming Language :: Python :: 2.7
